marketorestpython/__init__.py
marketorestpython/client.py
marketorestpython/helper/__init__.py
marketorestpython/helper/exceptions.py
marketorestpython/helper/http_lib.py
mintigo-marketo-rest/__init__.py
mintigo-marketo-rest/client.py
mintigo_marketo_rest-0.0.2.dist-info/METADATA
mintigo_marketo_rest-0.0.2.dist-info/RECORD
mintigo_marketo_rest-0.0.2.dist-info/WHEEL
mintigo_marketo_rest-0.0.2.dist-info/top_level.txt
mintigomarketorest/__init__.py
mintigomarketorest/client.py
